yo_claude/__init__.py
yo_claude/__main__.py
yo_claude/cli.py
yo_claude/config.py
yo_claude/core.py
yo_claude/logging.py
yo_claude/scheduler.py
yo_claude-0.0.1.dist-info/licenses/LICENSE
yo_claude-0.0.1.dist-info/METADATA
yo_claude-0.0.1.dist-info/WHEEL
yo_claude-0.0.1.dist-info/entry_points.txt
yo_claude-0.0.1.dist-info/top_level.txt
yo_claude-0.0.1.dist-info/RECORD
