Metadata-Version: 2.4
Name: yo-claude
Version: 0.0.1
Summary: Start your Claude session refresh early to avoid mid-work interruptions
Author-email: Daniel Murrell <dsmurrell@gmail.com>
License: MIT
Project-URL: Homepage, https://github.com/dsmurrell/yo-claude
Project-URL: Repository, https://github.com/dsmurrell/yo-claude.git
Project-URL: Issues, https://github.com/dsmurrell/yo-claude/issues
Keywords: claude,anthropic,cli,productivity,rate-limit
Classifier: Development Status :: 4 - Beta
Classifier: Environment :: Console
Classifier: Intended Audience :: Developers
Classifier: License :: OSI Approved :: MIT License
Classifier: Operating System :: OS Independent
Classifier: Programming Language :: Python :: 3
Classifier: Programming Language :: Python :: 3.9
Classifier: Programming Language :: Python :: 3.10
Classifier: Programming Language :: Python :: 3.11
Classifier: Programming Language :: Python :: 3.12
Classifier: Topic :: Utilities
Requires-Python: >=3.9
License-File: LICENSE
Requires-Dist: tomli>=2.0.0; python_version < "3.11"
Dynamic: license-file
